DYPMS/__init__.py
DYPMS/client.py
DYPMS/enums.py
DYPMS/api/__init__.py
DYPMS/api/get_simulate_portfolio_list.py
DYPMS/api/get_simulate_portfolio_net.py
DYPMS/api/get_simulate_portfolio_performance_indicators.py
DYPMS/api/get_simulate_portfolio_position.py
DYPMS/api/get_simulate_portfolio_position_hierarchy.py
DYPMS/api/get_style_attr_trend.py
DYPMS/api/heartbeat.py
DYPMS/api/util.py
dypms-0.1.dist-info/licenses/LICENSE
dypms-0.1.dist-info/METADATA
dypms-0.1.dist-info/WHEEL
dypms-0.1.dist-info/top_level.txt
dypms-0.1.dist-info/RECORD
